
{"items":[{"name":"Recycle.Api","href":"Recycle.Api.html","topicHref":"Recycle.Api.html","topicUid":"Recycle.Api","type":"Namespace","items":[{"name":"Program","href":"Recycle.Api.Program.html","topicHref":"Recycle.Api.Program.html","topicUid":"Recycle.Api.Program","type":"Class"},{"name":"Startup","href":"Recycle.Api.Startup.html","topicHref":"Recycle.Api.Startup.html","topicUid":"Recycle.Api.Startup","type":"Class"}]},{"name":"Recycle.Api.BackgroundServices","href":"Recycle.Api.BackgroundServices.html","topicHref":"Recycle.Api.BackgroundServices.html","topicUid":"Recycle.Api.BackgroundServices","type":"Namespace","items":[{"name":"EmailSenderBackgroundService","href":"Recycle.Api.BackgroundServices.EmailSenderBackgroundService.html","topicHref":"Recycle.Api.BackgroundServices.EmailSenderBackgroundService.html","topicUid":"Recycle.Api.BackgroundServices.EmailSenderBackgroundService","type":"Class"}]},{"name":"Recycle.Api.Controllers","href":"Recycle.Api.Controllers.html","topicHref":"Recycle.Api.Controllers.html","topicUid":"Recycle.Api.Controllers","type":"Namespace","items":[{"name":"ArticleController","href":"Recycle.Api.Controllers.ArticleController.html","topicHref":"Recycle.Api.Controllers.ArticleController.html","topicUid":"Recycle.Api.Controllers.ArticleController","type":"Class"},{"name":"AuthController","href":"Recycle.Api.Controllers.AuthController.html","topicHref":"Recycle.Api.Controllers.AuthController.html","topicUid":"Recycle.Api.Controllers.AuthController","type":"Class"},{"name":"LocationController","href":"Recycle.Api.Controllers.LocationController.html","topicHref":"Recycle.Api.Controllers.LocationController.html","topicUid":"Recycle.Api.Controllers.LocationController","type":"Class"},{"name":"MaterialController","href":"Recycle.Api.Controllers.MaterialController.html","topicHref":"Recycle.Api.Controllers.MaterialController.html","topicUid":"Recycle.Api.Controllers.MaterialController","type":"Class"},{"name":"PartController","href":"Recycle.Api.Controllers.PartController.html","topicHref":"Recycle.Api.Controllers.PartController.html","topicUid":"Recycle.Api.Controllers.PartController","type":"Class"},{"name":"ProductController","href":"Recycle.Api.Controllers.ProductController.html","topicHref":"Recycle.Api.Controllers.ProductController.html","topicUid":"Recycle.Api.Controllers.ProductController","type":"Class"},{"name":"TrashCanController","href":"Recycle.Api.Controllers.TrashCanController.html","topicHref":"Recycle.Api.Controllers.TrashCanController.html","topicUid":"Recycle.Api.Controllers.TrashCanController","type":"Class"}]},{"name":"Recycle.Api.Models.Articles","href":"Recycle.Api.Models.Articles.html","topicHref":"Recycle.Api.Models.Articles.html","topicUid":"Recycle.Api.Models.Articles","type":"Namespace","items":[{"name":"ArticleCreateModel","href":"Recycle.Api.Models.Articles.ArticleCreateModel.html","topicHref":"Recycle.Api.Models.Articles.ArticleCreateModel.html","topicUid":"Recycle.Api.Models.Articles.ArticleCreateModel","type":"Class"},{"name":"ArticleCreateModelExtensions","href":"Recycle.Api.Models.Articles.ArticleCreateModelExtensions.html","topicHref":"Recycle.Api.Models.Articles.ArticleCreateModelExtensions.html","topicUid":"Recycle.Api.Models.Articles.ArticleCreateModelExtensions","type":"Class"},{"name":"ArticleDetailModel","href":"Recycle.Api.Models.Articles.ArticleDetailModel.html","topicHref":"Recycle.Api.Models.Articles.ArticleDetailModel.html","topicUid":"Recycle.Api.Models.Articles.ArticleDetailModel","type":"Class"},{"name":"ArticleDetailModelExtensions","href":"Recycle.Api.Models.Articles.ArticleDetailModelExtensions.html","topicHref":"Recycle.Api.Models.Articles.ArticleDetailModelExtensions.html","topicUid":"Recycle.Api.Models.Articles.ArticleDetailModelExtensions","type":"Class"}]},{"name":"Recycle.Api.Models.Authorization","href":"Recycle.Api.Models.Authorization.html","topicHref":"Recycle.Api.Models.Authorization.html","topicUid":"Recycle.Api.Models.Authorization","type":"Namespace","items":[{"name":"LogInModel","href":"Recycle.Api.Models.Authorization.LogInModel.html","topicHref":"Recycle.Api.Models.Authorization.LogInModel.html","topicUid":"Recycle.Api.Models.Authorization.LogInModel","type":"Class"},{"name":"RegisterModel","href":"Recycle.Api.Models.Authorization.RegisterModel.html","topicHref":"Recycle.Api.Models.Authorization.RegisterModel.html","topicUid":"Recycle.Api.Models.Authorization.RegisterModel","type":"Class"},{"name":"TokenModel","href":"Recycle.Api.Models.Authorization.TokenModel.html","topicHref":"Recycle.Api.Models.Authorization.TokenModel.html","topicUid":"Recycle.Api.Models.Authorization.TokenModel","type":"Class"}]},{"name":"Recycle.Api.Models.Locations","href":"Recycle.Api.Models.Locations.html","topicHref":"Recycle.Api.Models.Locations.html","topicUid":"Recycle.Api.Models.Locations","type":"Namespace","items":[{"name":"LocationCreateModel","href":"Recycle.Api.Models.Locations.LocationCreateModel.html","topicHref":"Recycle.Api.Models.Locations.LocationCreateModel.html","topicUid":"Recycle.Api.Models.Locations.LocationCreateModel","type":"Class"},{"name":"LocationCreateModelExtentions","href":"Recycle.Api.Models.Locations.LocationCreateModelExtentions.html","topicHref":"Recycle.Api.Models.Locations.LocationCreateModelExtentions.html","topicUid":"Recycle.Api.Models.Locations.LocationCreateModelExtentions","type":"Class"},{"name":"LocationDetailModel","href":"Recycle.Api.Models.Locations.LocationDetailModel.html","topicHref":"Recycle.Api.Models.Locations.LocationDetailModel.html","topicUid":"Recycle.Api.Models.Locations.LocationDetailModel","type":"Class"},{"name":"LocationDetailModelExtensions","href":"Recycle.Api.Models.Locations.LocationDetailModelExtensions.html","topicHref":"Recycle.Api.Models.Locations.LocationDetailModelExtensions.html","topicUid":"Recycle.Api.Models.Locations.LocationDetailModelExtensions","type":"Class"}]},{"name":"Recycle.Api.Models.Materials","href":"Recycle.Api.Models.Materials.html","topicHref":"Recycle.Api.Models.Materials.html","topicUid":"Recycle.Api.Models.Materials","type":"Namespace","items":[{"name":"CategoryDetailModelExtentions","href":"Recycle.Api.Models.Materials.CategoryDetailModelExtentions.html","topicHref":"Recycle.Api.Models.Materials.CategoryDetailModelExtentions.html","topicUid":"Recycle.Api.Models.Materials.CategoryDetailModelExtentions","type":"Class"},{"name":"MaterialCreateModel","href":"Recycle.Api.Models.Materials.MaterialCreateModel.html","topicHref":"Recycle.Api.Models.Materials.MaterialCreateModel.html","topicUid":"Recycle.Api.Models.Materials.MaterialCreateModel","type":"Class"},{"name":"MaterialCreateModelExtentions","href":"Recycle.Api.Models.Materials.MaterialCreateModelExtentions.html","topicHref":"Recycle.Api.Models.Materials.MaterialCreateModelExtentions.html","topicUid":"Recycle.Api.Models.Materials.MaterialCreateModelExtentions","type":"Class"},{"name":"MaterialDetailModel","href":"Recycle.Api.Models.Materials.MaterialDetailModel.html","topicHref":"Recycle.Api.Models.Materials.MaterialDetailModel.html","topicUid":"Recycle.Api.Models.Materials.MaterialDetailModel","type":"Class"}]},{"name":"Recycle.Api.Models.Parts","href":"Recycle.Api.Models.Parts.html","topicHref":"Recycle.Api.Models.Parts.html","topicUid":"Recycle.Api.Models.Parts","type":"Namespace","items":[{"name":"PartCreateModel","href":"Recycle.Api.Models.Parts.PartCreateModel.html","topicHref":"Recycle.Api.Models.Parts.PartCreateModel.html","topicUid":"Recycle.Api.Models.Parts.PartCreateModel","type":"Class"},{"name":"PartDetailModel","href":"Recycle.Api.Models.Parts.PartDetailModel.html","topicHref":"Recycle.Api.Models.Parts.PartDetailModel.html","topicUid":"Recycle.Api.Models.Parts.PartDetailModel","type":"Class"},{"name":"ParttDetailModelExtensions","href":"Recycle.Api.Models.Parts.ParttDetailModelExtensions.html","topicHref":"Recycle.Api.Models.Parts.ParttDetailModelExtensions.html","topicUid":"Recycle.Api.Models.Parts.ParttDetailModelExtensions","type":"Class"}]},{"name":"Recycle.Api.Models.Products","href":"Recycle.Api.Models.Products.html","topicHref":"Recycle.Api.Models.Products.html","topicUid":"Recycle.Api.Models.Products","type":"Namespace","items":[{"name":"ProductCreateModel","href":"Recycle.Api.Models.Products.ProductCreateModel.html","topicHref":"Recycle.Api.Models.Products.ProductCreateModel.html","topicUid":"Recycle.Api.Models.Products.ProductCreateModel","type":"Class"},{"name":"ProductDetailModel","href":"Recycle.Api.Models.Products.ProductDetailModel.html","topicHref":"Recycle.Api.Models.Products.ProductDetailModel.html","topicUid":"Recycle.Api.Models.Products.ProductDetailModel","type":"Class"},{"name":"ProductDetailModelExtensions","href":"Recycle.Api.Models.Products.ProductDetailModelExtensions.html","topicHref":"Recycle.Api.Models.Products.ProductDetailModelExtensions.html","topicUid":"Recycle.Api.Models.Products.ProductDetailModelExtensions","type":"Class"}]},{"name":"Recycle.Api.Models.TrashCans","href":"Recycle.Api.Models.TrashCans.html","topicHref":"Recycle.Api.Models.TrashCans.html","topicUid":"Recycle.Api.Models.TrashCans","type":"Namespace","items":[{"name":"TrashCanCreateModel","href":"Recycle.Api.Models.TrashCans.TrashCanCreateModel.html","topicHref":"Recycle.Api.Models.TrashCans.TrashCanCreateModel.html","topicUid":"Recycle.Api.Models.TrashCans.TrashCanCreateModel","type":"Class"},{"name":"TrashCanCreateModelExtentions","href":"Recycle.Api.Models.TrashCans.TrashCanCreateModelExtentions.html","topicHref":"Recycle.Api.Models.TrashCans.TrashCanCreateModelExtentions.html","topicUid":"Recycle.Api.Models.TrashCans.TrashCanCreateModelExtentions","type":"Class"},{"name":"TrashCanDetailModel","href":"Recycle.Api.Models.TrashCans.TrashCanDetailModel.html","topicHref":"Recycle.Api.Models.TrashCans.TrashCanDetailModel.html","topicUid":"Recycle.Api.Models.TrashCans.TrashCanDetailModel","type":"Class"},{"name":"TrashCanDetailModelExtensions","href":"Recycle.Api.Models.TrashCans.TrashCanDetailModelExtensions.html","topicHref":"Recycle.Api.Models.TrashCans.TrashCanDetailModelExtensions.html","topicUid":"Recycle.Api.Models.TrashCans.TrashCanDetailModelExtensions","type":"Class"}]},{"name":"Recycle.Api.Services","href":"Recycle.Api.Services.html","topicHref":"Recycle.Api.Services.html","topicUid":"Recycle.Api.Services","type":"Namespace","items":[{"name":"EmailSenderService","href":"Recycle.Api.Services.EmailSenderService.html","topicHref":"Recycle.Api.Services.EmailSenderService.html","topicUid":"Recycle.Api.Services.EmailSenderService","type":"Class"}]},{"name":"Recycle.Api.Settings","href":"Recycle.Api.Settings.html","topicHref":"Recycle.Api.Settings.html","topicUid":"Recycle.Api.Settings","type":"Namespace","items":[{"name":"SmtpSettings","href":"Recycle.Api.Settings.SmtpSettings.html","topicHref":"Recycle.Api.Settings.SmtpSettings.html","topicUid":"Recycle.Api.Settings.SmtpSettings","type":"Class"}]},{"name":"Recycle.Api.Utilities","href":"Recycle.Api.Utilities.html","topicHref":"Recycle.Api.Utilities.html","topicUid":"Recycle.Api.Utilities","type":"Namespace","items":[{"name":"ApplicationMapper","href":"Recycle.Api.Utilities.ApplicationMapper.html","topicHref":"Recycle.Api.Utilities.ApplicationMapper.html","topicUid":"Recycle.Api.Utilities.ApplicationMapper","type":"Class"},{"name":"ClaimsPrincipalExtensions","href":"Recycle.Api.Utilities.ClaimsPrincipalExtensions.html","topicHref":"Recycle.Api.Utilities.ClaimsPrincipalExtensions.html","topicUid":"Recycle.Api.Utilities.ClaimsPrincipalExtensions","type":"Class"},{"name":"IApplicationMapper","href":"Recycle.Api.Utilities.IApplicationMapper.html","topicHref":"Recycle.Api.Utilities.IApplicationMapper.html","topicUid":"Recycle.Api.Utilities.IApplicationMapper","type":"Interface"}]},{"name":"Recycle.Data","href":"Recycle.Data.html","topicHref":"Recycle.Data.html","topicUid":"Recycle.Data","type":"Namespace","items":[{"name":"AppDbContext","href":"Recycle.Data.AppDbContext.html","topicHref":"Recycle.Data.AppDbContext.html","topicUid":"Recycle.Data.AppDbContext","type":"Class"}]},{"name":"Recycle.Data.Entities","href":"Recycle.Data.Entities.html","topicHref":"Recycle.Data.Entities.html","topicUid":"Recycle.Data.Entities","type":"Namespace","items":[{"name":"Article","href":"Recycle.Data.Entities.Article.html","topicHref":"Recycle.Data.Entities.Article.html","topicUid":"Recycle.Data.Entities.Article","type":"Class"},{"name":"ArticleExtensions","href":"Recycle.Data.Entities.ArticleExtensions.html","topicHref":"Recycle.Data.Entities.ArticleExtensions.html","topicUid":"Recycle.Data.Entities.ArticleExtensions","type":"Class"},{"name":"Email","href":"Recycle.Data.Entities.Email.html","topicHref":"Recycle.Data.Entities.Email.html","topicUid":"Recycle.Data.Entities.Email","type":"Class"},{"name":"Location","href":"Recycle.Data.Entities.Location.html","topicHref":"Recycle.Data.Entities.Location.html","topicUid":"Recycle.Data.Entities.Location","type":"Class"},{"name":"LocationExtentions","href":"Recycle.Data.Entities.LocationExtentions.html","topicHref":"Recycle.Data.Entities.LocationExtentions.html","topicUid":"Recycle.Data.Entities.LocationExtentions","type":"Class"},{"name":"Material","href":"Recycle.Data.Entities.Material.html","topicHref":"Recycle.Data.Entities.Material.html","topicUid":"Recycle.Data.Entities.Material","type":"Class"},{"name":"MaterialExtentions","href":"Recycle.Data.Entities.MaterialExtentions.html","topicHref":"Recycle.Data.Entities.MaterialExtentions.html","topicUid":"Recycle.Data.Entities.MaterialExtentions","type":"Class"},{"name":"Part","href":"Recycle.Data.Entities.Part.html","topicHref":"Recycle.Data.Entities.Part.html","topicUid":"Recycle.Data.Entities.Part","type":"Class"},{"name":"PartExtentions","href":"Recycle.Data.Entities.PartExtentions.html","topicHref":"Recycle.Data.Entities.PartExtentions.html","topicUid":"Recycle.Data.Entities.PartExtentions","type":"Class"},{"name":"PartMaterial","href":"Recycle.Data.Entities.PartMaterial.html","topicHref":"Recycle.Data.Entities.PartMaterial.html","topicUid":"Recycle.Data.Entities.PartMaterial","type":"Class"},{"name":"PartType","href":"Recycle.Data.Entities.PartType.html","topicHref":"Recycle.Data.Entities.PartType.html","topicUid":"Recycle.Data.Entities.PartType","type":"Enum"},{"name":"Product","href":"Recycle.Data.Entities.Product.html","topicHref":"Recycle.Data.Entities.Product.html","topicUid":"Recycle.Data.Entities.Product","type":"Class"},{"name":"ProductExtentions","href":"Recycle.Data.Entities.ProductExtentions.html","topicHref":"Recycle.Data.Entities.ProductExtentions.html","topicUid":"Recycle.Data.Entities.ProductExtentions","type":"Class"},{"name":"ProductPart","href":"Recycle.Data.Entities.ProductPart.html","topicHref":"Recycle.Data.Entities.ProductPart.html","topicUid":"Recycle.Data.Entities.ProductPart","type":"Class"},{"name":"TrashCan","href":"Recycle.Data.Entities.TrashCan.html","topicHref":"Recycle.Data.Entities.TrashCan.html","topicUid":"Recycle.Data.Entities.TrashCan","type":"Class"},{"name":"TrashCan.TrashCanType","href":"Recycle.Data.Entities.TrashCan.TrashCanType.html","topicHref":"Recycle.Data.Entities.TrashCan.TrashCanType.html","topicUid":"Recycle.Data.Entities.TrashCan.TrashCanType","type":"Enum"},{"name":"TrashCanExtentions","href":"Recycle.Data.Entities.TrashCanExtentions.html","topicHref":"Recycle.Data.Entities.TrashCanExtentions.html","topicUid":"Recycle.Data.Entities.TrashCanExtentions","type":"Class"},{"name":"TrashCanMaterialLocation","href":"Recycle.Data.Entities.TrashCanMaterialLocation.html","topicHref":"Recycle.Data.Entities.TrashCanMaterialLocation.html","topicUid":"Recycle.Data.Entities.TrashCanMaterialLocation","type":"Class"}]},{"name":"Recycle.Data.Entities.Identity","href":"Recycle.Data.Entities.Identity.html","topicHref":"Recycle.Data.Entities.Identity.html","topicUid":"Recycle.Data.Entities.Identity","type":"Namespace","items":[{"name":"ApplicationUser","href":"Recycle.Data.Entities.Identity.ApplicationUser.html","topicHref":"Recycle.Data.Entities.Identity.ApplicationUser.html","topicUid":"Recycle.Data.Entities.Identity.ApplicationUser","type":"Class"},{"name":"Role","href":"Recycle.Data.Entities.Identity.Role.html","topicHref":"Recycle.Data.Entities.Identity.Role.html","topicUid":"Recycle.Data.Entities.Identity.Role","type":"Class"},{"name":"UserRole","href":"Recycle.Data.Entities.Identity.UserRole.html","topicHref":"Recycle.Data.Entities.Identity.UserRole.html","topicUid":"Recycle.Data.Entities.Identity.UserRole","type":"Class"}]},{"name":"Recycle.Data.Interfaces","href":"Recycle.Data.Interfaces.html","topicHref":"Recycle.Data.Interfaces.html","topicUid":"Recycle.Data.Interfaces","type":"Namespace","items":[{"name":"ITrackable","href":"Recycle.Data.Interfaces.ITrackable.html","topicHref":"Recycle.Data.Interfaces.ITrackable.html","topicUid":"Recycle.Data.Interfaces.ITrackable","type":"Interface"},{"name":"ITrackableExtensions","href":"Recycle.Data.Interfaces.ITrackableExtensions.html","topicHref":"Recycle.Data.Interfaces.ITrackableExtensions.html","topicUid":"Recycle.Data.Interfaces.ITrackableExtensions","type":"Class"}]},{"name":"Recycle.Data.Migrations","href":"Recycle.Data.Migrations.html","topicHref":"Recycle.Data.Migrations.html","topicUid":"Recycle.Data.Migrations","type":"Namespace","items":[{"name":"ConecctionTables","href":"Recycle.Data.Migrations.ConecctionTables.html","topicHref":"Recycle.Data.Migrations.ConecctionTables.html","topicUid":"Recycle.Data.Migrations.ConecctionTables","type":"Class"},{"name":"Int","href":"Recycle.Data.Migrations.Int.html","topicHref":"Recycle.Data.Migrations.Int.html","topicUid":"Recycle.Data.Migrations.Int","type":"Class"},{"name":"RegionsRemoved","href":"Recycle.Data.Migrations.RegionsRemoved.html","topicHref":"Recycle.Data.Migrations.RegionsRemoved.html","topicUid":"Recycle.Data.Migrations.RegionsRemoved","type":"Class"},{"name":"RegisterModel","href":"Recycle.Data.Migrations.RegisterModel.html","topicHref":"Recycle.Data.Migrations.RegisterModel.html","topicUid":"Recycle.Data.Migrations.RegisterModel","type":"Class"},{"name":"TokenGenetaring","href":"Recycle.Data.Migrations.TokenGenetaring.html","topicHref":"Recycle.Data.Migrations.TokenGenetaring.html","topicUid":"Recycle.Data.Migrations.TokenGenetaring","type":"Class"},{"name":"userChangetNotNullable","href":"Recycle.Data.Migrations.userChangetNotNullable.html","topicHref":"Recycle.Data.Migrations.userChangetNotNullable.html","topicUid":"Recycle.Data.Migrations.userChangetNotNullable","type":"Class"},{"name":"userDeletedProperty","href":"Recycle.Data.Migrations.userDeletedProperty.html","topicHref":"Recycle.Data.Migrations.userDeletedProperty.html","topicUid":"Recycle.Data.Migrations.userDeletedProperty","type":"Class"}]}],"memberLayout":"SamePage","pdf":true}
